setup.cfg
setup.py
mako_pipeline/__init__.py
mako_pipeline/assets.py
mako_pipeline.egg-info/PKG-INFO
mako_pipeline.egg-info/SOURCES.txt
mako_pipeline.egg-info/dependency_links.txt
mako_pipeline.egg-info/requires.txt
mako_pipeline.egg-info/top_level.txt