Metadata-Version: 1.0
Name: mako-pipeline
Version: 0.0.1
Summary: Manage assets on mako templates
Home-page: https://github.com/rcmachado/mako-pipeline
Author: Rodrigo Machado
Author-email: rcmachado@gmail.com
License: MIT
Platform: UNKNOWN
